OneNeuron/__init__.py
OneNeuron/perceptron.py
OneNeuron_pypi_nkumar43-0.0.1.dist-info/LICENSE
OneNeuron_pypi_nkumar43-0.0.1.dist-info/METADATA
OneNeuron_pypi_nkumar43-0.0.1.dist-info/WHEEL
OneNeuron_pypi_nkumar43-0.0.1.dist-info/top_level.txt
OneNeuron_pypi_nkumar43-0.0.1.dist-info/RECORD
