Metadata-Version: 2.1
Name: OneNeuron-pypi-nkumar43
Version: 0.0.1
Summary: It's an implementation of Perceptron
Home-page: https://github.com/nkumar43/OneNeuron_pypi
Author: nkumar43
Author-email: neerajk.eebitm@gmail.com
License: UNKNOWN
Project-URL: Bug Tracker, https://github.com/nkumar43/OneNeuron_pypi/issues
Platform: UNKNOWN
Classifier: Programming Language :: Python :: 3
Classifier: License :: OSI Approved :: MIT License
Classifier: Operating System :: OS Independent
Requires-Python: >=3.7
License-File: LICENSE
Requires-Dist: numpy
Requires-Dist: tqdm
